cd_rss_reader/__init__.py
cd_rss_reader/rss_reader.py
cd_rss_reader/version.py
cd_rss_reader/Examples/example.py
cd_rss_reader-0.0.1.dist-info/LICENSE.md
cd_rss_reader-0.0.1.dist-info/LICENSE.txt
cd_rss_reader-0.0.1.dist-info/METADATA
cd_rss_reader-0.0.1.dist-info/WHEEL
cd_rss_reader-0.0.1.dist-info/top_level.txt
cd_rss_reader-0.0.1.dist-info/RECORD
