Metadata-Version: 2.1
Name: cd-rss-reader
Version: 0.0.1
Summary: The RSSReader is a Python utility for effortlessly fetching and parsing RSS and Atom feeds.
Author-email: Code Docta <codedocta@gmail.com>
License: MIT
Project-URL: homepage, https://codedocta.com
Project-URL: Bug-Reports, https://github.com/codedocta/cd_rss_reader/issues
Project-URL: Source, https://github.com/codedocta/cd_rss_reader/
Classifier: Development Status :: 4 - Beta
Classifier: License :: OSI Approved :: MIT License
Classifier: Programming Language :: Python :: 3
Classifier: Operating System :: OS Independent
Requires-Python: >=3.6
License-File: LICENSE.md
License-File: LICENSE.txt
Requires-Dist: feedparser ==6.0.10
Requires-Dist: lxml ==4.9.3
Requires-Dist: sgmllib3k ==1.0.0
